[
   {
      "date":"June 1, 2015",
      "image":"http://cdn2.ubergizmo.com/wp-content/uploads/2015/04/backup-android.jpg",
      "text":"The Cy-Ranch App Begins Development",
      "link":"#"
   },
   {
      "date":"December 13, 2015",
      "image":"http://cdn.instructables.com/FA6/6TS8/GDVZF6IQ/FA66TS8GDVZF6IQ.MEDIUM.jpg",
      "text":"Major Update! You can now access your grades.",
      "link":"#"
   },
   {
      "date":"November 24, 2016",
      "image":"http://cafeescadrille.com/wp-content/uploads/2015/10/thanksgiving.jpg",
      "text":"Happy Thanksgiving!",
      "link":"#"
   }
]